Metadata-Version: 2.1
Name: calcymath
Version: 0.0.6
Summary: A simple math library
Home-page: https://github.com/hariprasad1003/calcy-math
Author: Hari Prasad
Author-email: hariprasadgurunathan10@gmail.com
License: MIT
Platform: UNKNOWN
Classifier: Programming Language :: Python :: 3
Classifier: License :: OSI Approved :: MIT License
Classifier: Operating System :: OS Independent
Requires-Python: >=3.7
